{"skins":[{"localization_name":"Barmaid","geometry":"geometry.humanoid.customSlim","texture":"Barmaid_slim.png","type":"free"},{"localization_name":"Barman","geometry":"geometry.humanoid.custom","texture":"Barman.png","type":"free"},{"localization_name":"Baron","geometry":"geometry.humanoid.custom","texture":"Baron.png","type":"free"},{"localization_name":"Baroness","geometry":"geometry.humanoid.custom","texture":"Baroness.png","type":"free"},{"localization_name":"Blacksmith","geometry":"geometry.humanoid.custom","texture":"Blacksmith.png","type":"free"},{"localization_name":"Baker","geometry":"geometry.humanoid.custom","texture":"Baker.png","type":"free"},{"localization_name":"Butcher","geometry":"geometry.humanoid.custom","texture":"ButcherSkin.png","type":"free"},{"localization_name":"Carpenter","geometry":"geometry.humanoid.custom","texture":"Carpenter.png","type":"free"},{"localization_name":"Chef","geometry":"geometry.humanoid.custom","texture":"Chef.png","type":"free"},{"localization_name":"HolyMan","geometry":"geometry.humanoid.custom","texture":"HolyMan.png","type":"free"},{"localization_name":"HolyWoman","geometry":"geometry.humanoid.custom","texture":"HolyWoman.png","type":"free"},{"localization_name":"Jailer","geometry":"geometry.humanoid.custom","texture":"Jailer.png","type":"free"},{"localization_name":"King","geometry":"geometry.humanoid.custom","texture":"King.png","type":"free"},{"localization_name":"Mage","geometry":"geometry.humanoid.custom","texture":"Mage.png","type":"free"},{"localization_name":"Postman","geometry":"geometry.humanoid.custom","texture":"Postman.png","type":"free"},{"localization_name":"Queen","geometry":"geometry.humanoid.custom","texture":"Queen.png","type":"free"},{"localization_name":"Shoemaker","geometry":"geometry.humanoid.custom","texture":"Shoemaker.png","type":"free"},{"localization_name":"Victorian","geometry":"geometry.humanoid.custom","texture":"Victorian.png","type":"free"},{"localization_name":"Watchman","geometry":"geometry.humanoid.custom","texture":"Watchman.png","type":"free"},{"localization_name":"WeaponSmith","geometry":"geometry.humanoid.custom","texture":"WeaponSmith.png","type":"free"}],"serialize_name":"city-folk-skin-pack","localization_name":"city-folk-skin-pack"}